chattypy/__init__.py
chattypy/bot.py
chattypy-0.1.3.dist-info/LICENSE.txt
chattypy-0.1.3.dist-info/METADATA
chattypy-0.1.3.dist-info/WHEEL
chattypy-0.1.3.dist-info/top_level.txt
chattypy-0.1.3.dist-info/RECORD
