Metadata-Version: 2.1
Name: chattypy
Version: 0.1.3
Summary: ChattyPy is a library made in Python for making Chatty bots.
Home-page: https://github.com/lafkpages/ChattyPy
Author: LuisAFK
Author-email: so.yl.a.fk@googlemail.com
License: UNKNOWN
Project-URL: Documentation, https://github.com/lafkpages/ChattyPy
Project-URL: Source Code, https://github.com/lafkpages/ChattyPy
Project-URL: Bug Tracker, https://github.com/lafkpages/ChattyPy/issues
Project-URL: Discussions, https://github.com/lafkpages/ChattyPy/discussions
Keywords: chatty,bot,api,python,chattypy
Platform: UNKNOWN
Classifier: Programming Language :: Python :: 3
Classifier: License :: OSI Approved :: GNU Affero General Public License v3
Classifier: Operating System :: OS Independent
Requires-Python: >=3.6
Requires-Dist: websocket-client
